cloud_pits-0.0.1.data/scripts/cloudpits_create_ondemand_jm
cloud_pits-0.0.1.data/scripts/cloudpits_simulation
cloud_pits-0.0.1.data/scripts/cloudpits_to_execute
cloudpits/__init__.py
cloudpits/instance_operations.py
cloudpits/pseudo_instance_operations.py
cloudpits/rds_config.py
cloudpits/rds_operations.py
cloudpits/save_interpols.py
cloudpits/save_performance.py
cloud_pits-0.0.1.dist-info/LICENSE
cloud_pits-0.0.1.dist-info/METADATA
cloud_pits-0.0.1.dist-info/WHEEL
cloud_pits-0.0.1.dist-info/top_level.txt
cloud_pits-0.0.1.dist-info/RECORD
